pemacs/__init__.py
pemacs-0.1.0.dist-info/WHEEL
pemacs-0.1.0.dist-info/METADATA
pemacs-0.1.0.dist-info/RECORD
